EB/__init__.py
EB/ensemblebuilder
EB/builder/__init__.py
EB/builder/eb_main.py
EB/builder/exhaustive/__init__.py
EB/builder/exhaustive/exhaustive.py
EB/builder/exhaustive/exhaustive_io.py
EB/builder/fastheuristic/__init__.py
EB/builder/fastheuristic/fastheuristic.py
EB/builder/fastheuristic/fastheuristic_io.py
EB/builder/postanalysis/__init__.py
EB/builder/postanalysis/postanalysis.py
EB/builder/postanalysis/postanalysis_io.py
EB/builder/slowheuristic/__init__.py
EB/builder/slowheuristic/slowheuristic.py
EB/builder/slowheuristic/slowheuristic_io.py
EB/builder/splitter/__init__.py
EB/builder/splitter/splitter.py
EB/builder/splitter/splitter_io.py
EB/builder/utilities/__init__.py
EB/builder/utilities/classification.py
EB/builder/utilities/csv_interface.py
EB/builder/utilities/ensemble_storage.py
EB/builder/utilities/molecules.py
EB/builder/utilities/output.py
EB/builder/utilities/performance.py
EB/builder/utilities/screener.py
EB-0.1.5.data/scripts/ensemblebuilder
EB-0.1.5.dist-info/DESCRIPTION.rst
EB-0.1.5.dist-info/METADATA
EB-0.1.5.dist-info/RECORD
EB-0.1.5.dist-info/WHEEL
EB-0.1.5.dist-info/metadata.json
EB-0.1.5.dist-info/top_level.txt
