Metadata-Version: 1.1
Name: EB
Version: 0.1.5
Summary: Ensemble Builder
Home-page: https://github.com/rvswift/EB
Author: Rob Swift
Author-email: robvswift@gmail.com
License: BSD
Keywords: EB
Platform: UNKNOWN
Classifier: Development Status :: 2 - Pre-Alpha
Classifier: Intended Audience :: Developers
Classifier: License :: OSI Approved :: BSD License
Classifier: Natural Language :: English
Classifier: Programming Language :: Python :: 2
Classifier: Programming Language :: Python :: 2.6
Classifier: Programming Language :: Python :: 2.7
Classifier: Programming Language :: Python :: 3
Classifier: Programming Language :: Python :: 3.3
Classifier: Programming Language :: Python :: 3.4
